domainbigdata/__init__.py
domainbigdata/cli.py
domainbigdata/domainbigdata.py
domainbigdata-1.1.1.dist-info/LICENSE
domainbigdata-1.1.1.dist-info/METADATA
domainbigdata-1.1.1.dist-info/WHEEL
domainbigdata-1.1.1.dist-info/entry_points.txt
domainbigdata-1.1.1.dist-info/top_level.txt
domainbigdata-1.1.1.dist-info/zip-safe
domainbigdata-1.1.1.dist-info/RECORD
