Metadata-Version: 2.1
Name: domainbigdata
Version: 1.1.1
Summary: Python wrapper for DomainBigData.com (no API available)
Home-page: https://github.com/wesinator/domainbigdata-python
Author: wesinator
License: UNKNOWN
Keywords: domainbigdata
Platform: UNKNOWN
Classifier: Intended Audience :: Developers
Classifier: License :: OSI Approved :: GNU General Public License v3 or later (GPLv3+)
Classifier: Natural Language :: English
Classifier: Programming Language :: Python :: 3
Classifier: Programming Language :: Python :: 3.5
Classifier: Programming Language :: Python :: 3.6
Classifier: Programming Language :: Python :: 3.7
Requires-Dist: beautifulsoup4
Requires-Dist: click
Requires-Dist: requests
